pyw/__init__.py
pyw_cv-0.0.0.post1.dist-info/METADATA
pyw_cv-0.0.0.post1.dist-info/WHEEL
pyw_cv-0.0.0.post1.dist-info/licenses/LICENSE
pyw_cv-0.0.0.post1.dist-info/RECORD
