Metadata-Version: 2.4
Name: pyw-cv
Version: 0.0.0.post1
Summary: Computer vision bundle (vision + motion)
Project-URL: Homepage, https://github.com/pythonWoods/pyw-cv
Project-URL: Documentation, https://pythonwoods.dev/docs/pyw-cv/latest/
Project-URL: Issues, https://github.com/pythonWoods/pyw-cv/issues
Project-URL: Changelog, https://github.com/pythonWoods/pyw-cv/releases
Author: pythonWoods
License: MIT
License-File: LICENSE
Classifier: Development Status :: 2 - Pre-Alpha
Classifier: License :: OSI Approved :: MIT License
Classifier: Programming Language :: Python :: 3 :: Only
Classifier: Programming Language :: Python :: 3.11
Classifier: Typing :: Typed
Requires-Python: >=3.9
Requires-Dist: pyw-core>=0.0.0
Requires-Dist: pyw-motion>=0.0.0
Requires-Dist: pyw-vision>=0.0.0
